{"$category":"crawled","mainimg":"http://file29.mafengwo.net/M00/3B/6A/wKgBpVX362eAWT79AAu1S7Radvc69.book.w230.jpeg","addname":"因特拉肯","tags":"<span>少女峰</span>\n                    <span>湖光山色</span>\n                    <span>勃朗峰</span>\n                    <span>滑翔</span>\n                <div class=\"clear\"></div>","abstracts":"<p><strong>简介</strong> 地处伯尔尼高地中心的因特拉肯，位于图恩湖和布里恩湖两个湖泊之间。这是瑞士一个闻名遐迩的观光小镇，坐落在鼎鼎大名的少女峰脚下，也是前往少女峰的必经之地。除了拥有湖光山色，因特拉肯小镇内的建筑也十分吸引人，小巧可爱的木屋，五颜六色的砖瓦，都让游客有仿佛置身童话世界之感。</p>","imgs":"<li class=\"scroll-content-item\">\n                    <a href=\"javascript:void(0);\" class=\"on_fous preview_btn\" data-paper_num=\"0\">\n                        <img src=\"http://file29.mafengwo.net/M00/3B/6A/wKgBpVX362eAWT79AAu1S7Radvc69.book.w130.jpeg\" width=\"138\" height=\"195\">\n                        <span>点击<br>预览</span>\n                    </a>\n                </li>\n                            <li class=\"scroll-content-item\">\n                    <a href=\"javascript:void(0);\" class=\"on_fous preview_btn\" data-paper_num=\"1\">\n                        <img src=\"http://file29.mafengwo.net/M00/3B/6A/wKgBpVX362eABMdIAA0gyOfGeTY48.book.w130.jpeg\" width=\"138\" height=\"195\">\n                        <span>点击<br>预览</span>\n                    </a>\n                </li>\n                            <li class=\"scroll-content-item\">\n                    <a href=\"javascript:void(0);\" class=\"on_fous preview_btn\" data-paper_num=\"2\">\n                        <img src=\"http://file30.mafengwo.net/M00/3B/6B/wKgBpVX362eAP9lkAAxZIUqrtv851.book.w130.jpeg\" width=\"138\" height=\"195\">\n                        <span>点击<br>预览</span>\n                    </a>\n                </li>\n                            <li class=\"scroll-content-item\">\n                    <a href=\"javascript:void(0);\" class=\"on_fous preview_btn\" data-paper_num=\"3\">\n                        <img src=\"http://file30.mafengwo.net/M00/3B/6B/wKgBpVX362eABHctAAyGeNe4gpQ54.book.w130.jpeg\" width=\"138\" height=\"195\">\n                        <span>点击<br>预览</span>\n                    </a>\n                </li>\n                            <li class=\"scroll-content-item\">\n                    <a href=\"javascript:void(0);\" class=\"on_fous preview_btn\" data-paper_num=\"4\">\n                        <img src=\"http://file29.mafengwo.net/M00/3B/6C/wKgBpVX362iATtGkAAv_o6JqXj870.book.w130.jpeg\" width=\"138\" height=\"195\">\n                        <span>点击<br>预览</span>\n                    </a>\n                </li>\n                            <li class=\"scroll-content-item\">\n                    <a href=\"javascript:void(0);\" class=\"on_fous preview_btn\" data-paper_num=\"5\">\n                        <img src=\"http://file29.mafengwo.net/M00/3B/6C/wKgBpVX362iARTx1AAtoLlDFn5I24.book.w130.jpeg\" width=\"138\" height=\"195\">\n                        <span>点击<br>预览</span>\n                    </a>\n                </li>\n                            <li class=\"scroll-content-item\">\n                    <a href=\"javascript:void(0);\" class=\"on_fous preview_btn\" data-paper_num=\"6\">\n                        <img src=\"http://file29.mafengwo.net/M00/3B/6C/wKgBpVX362iAMiiUAAyMjsQpKzY02.book.w130.jpeg\" width=\"138\" height=\"195\">\n                        <span>点击<br>预览</span>\n                    </a>\n                </li>\n                            <li class=\"scroll-content-item\">\n                    <a href=\"javascript:void(0);\" class=\"on_fous preview_btn\" data-paper_num=\"7\">\n                        <img src=\"http://file30.mafengwo.net/M00/3B/6D/wKgBpVX362mALiG_AAumkMku2CI70.book.w130.jpeg\" width=\"138\" height=\"195\">\n                        <span>点击<br>预览</span>\n                    </a>\n                </li>\n                            <li class=\"scroll-content-item\">\n                    <a href=\"javascript:void(0);\" class=\"on_fous preview_btn\" data-paper_num=\"8\">\n                        <img src=\"http://file29.mafengwo.net/M00/3B/6E/wKgBpVX362mABBTvAAuoyCSo12801.book.w130.jpeg\" width=\"138\" height=\"195\">\n                        <span>点击<br>预览</span>\n                    </a>\n                </li>\n                            <li class=\"scroll-content-item\">\n                    <a href=\"javascript:void(0);\" class=\"on_fous preview_btn\" data-paper_num=\"9\">\n                        <img src=\"http://file29.mafengwo.net/M00/3B/70/wKgBpVX362mAN2ZGAAv15ZfrtbQ61.book.w130.jpeg\" width=\"138\" height=\"195\">\n                        <span>点击<br>预览</span>\n                    </a>\n                </li>\n                            <li class=\"scroll-content-item\">\n                    <a href=\"javascript:void(0);\" class=\"on_fous preview_btn\" data-paper_num=\"10\">\n                        <img src=\"http://file30.mafengwo.net/M00/3B/71/wKgBpVX362mAf-ByAAqCn4qpkS098.book.w130.jpeg\" width=\"138\" height=\"195\">\n                        <span>点击<br>预览</span>\n                    </a>\n                </li>\n                            <li class=\"scroll-content-item\">\n                    <a href=\"javascript:void(0);\" class=\"on_fous preview_btn\" data-paper_num=\"11\">\n                        <img src=\"http://file29.mafengwo.net/M00/3B/72/wKgBpVX362qAT5XqAAxehhbTL2I71.book.w130.jpeg\" width=\"138\" height=\"195\">\n                        <span>点击<br>预览</span>\n                    </a>\n                </li>\n                            <li class=\"scroll-content-item\">\n                    <a href=\"javascript:void(0);\" class=\"on_fous preview_btn\" data-paper_num=\"12\">\n                        <img src=\"http://file29.mafengwo.net/M00/3B/72/wKgBpVX362qASBcMAAVu_uGx59c95.book.w130.jpeg\" width=\"138\" height=\"195\">\n                        <span>点击<br>预览</span>\n                    </a>\n                </li>"}{"$category":"crawled","mainimg":"http://file29.mafengwo.net/M00/3B/6A/wKgBpVX362eAWT79AAu1S7Radvc69.book.w230.jpeg","addname":"因特拉肯","tags":"<span>少女峰</span>\n                    <span>湖光山色</span>\n                    <span>勃朗峰</span>\n                    <span>滑翔</span>\n                <div class=\"clear\"></div>","abstracts":"<p><strong>简介</strong> 地处伯尔尼高地中心的因特拉肯，位于图恩湖和布里恩湖两个湖泊之间。这是瑞士一个闻名遐迩的观光小镇，坐落在鼎鼎大名的少女峰脚下，也是前往少女峰的必经之地。除了拥有湖光山色，因特拉肯小镇内的建筑也十分吸引人，小巧可爱的木屋，五颜六色的砖瓦，都让游客有仿佛置身童话世界之感。</p>","imgs":"<li class=\"scroll-content-item\">\n                    <a href=\"javascript:void(0);\" class=\"on_fous preview_btn\" data-paper_num=\"0\">\n                        <img src=\"http://file29.mafengwo.net/M00/3B/6A/wKgBpVX362eAWT79AAu1S7Radvc69.book.w130.jpeg\" width=\"138\" height=\"195\">\n                        <span>点击<br>预览</span>\n                    </a>\n                </li>\n                            <li class=\"scroll-content-item\">\n                    <a href=\"javascript:void(0);\" class=\"on_fous preview_btn\" data-paper_num=\"1\">\n                        <img src=\"http://file29.mafengwo.net/M00/3B/6A/wKgBpVX362eABMdIAA0gyOfGeTY48.book.w130.jpeg\" width=\"138\" height=\"195\">\n                        <span>点击<br>预览</span>\n                    </a>\n                </li>\n                            <li class=\"scroll-content-item\">\n                    <a href=\"javascript:void(0);\" class=\"on_fous preview_btn\" data-paper_num=\"2\">\n                        <img src=\"http://file30.mafengwo.net/M00/3B/6B/wKgBpVX362eAP9lkAAxZIUqrtv851.book.w130.jpeg\" width=\"138\" height=\"195\">\n                        <span>点击<br>预览</span>\n                    </a>\n                </li>\n                            <li class=\"scroll-content-item\">\n                    <a href=\"javascript:void(0);\" class=\"on_fous preview_btn\" data-paper_num=\"3\">\n                        <img src=\"http://file30.mafengwo.net/M00/3B/6B/wKgBpVX362eABHctAAyGeNe4gpQ54.book.w130.jpeg\" width=\"138\" height=\"195\">\n                        <span>点击<br>预览</span>\n                    </a>\n                </li>\n                            <li class=\"scroll-content-item\">\n                    <a href=\"javascript:void(0);\" class=\"on_fous preview_btn\" data-paper_num=\"4\">\n                        <img src=\"http://file29.mafengwo.net/M00/3B/6C/wKgBpVX362iATtGkAAv_o6JqXj870.book.w130.jpeg\" width=\"138\" height=\"195\">\n                        <span>点击<br>预览</span>\n                    </a>\n                </li>\n                            <li class=\"scroll-content-item\">\n                    <a href=\"javascript:void(0);\" class=\"on_fous preview_btn\" data-paper_num=\"5\">\n                        <img src=\"http://file29.mafengwo.net/M00/3B/6C/wKgBpVX362iARTx1AAtoLlDFn5I24.book.w130.jpeg\" width=\"138\" height=\"195\">\n                        <span>点击<br>预览</span>\n                    </a>\n                </li>\n                            <li class=\"scroll-content-item\">\n                    <a href=\"javascript:void(0);\" class=\"on_fous preview_btn\" data-paper_num=\"6\">\n                        <img src=\"http://file29.mafengwo.net/M00/3B/6C/wKgBpVX362iAMiiUAAyMjsQpKzY02.book.w130.jpeg\" width=\"138\" height=\"195\">\n                        <span>点击<br>预览</span>\n                    </a>\n                </li>\n                            <li class=\"scroll-content-item\">\n                    <a href=\"javascript:void(0);\" class=\"on_fous preview_btn\" data-paper_num=\"7\">\n                        <img src=\"http://file30.mafengwo.net/M00/3B/6D/wKgBpVX362mALiG_AAumkMku2CI70.book.w130.jpeg\" width=\"138\" height=\"195\">\n                        <span>点击<br>预览</span>\n                    </a>\n                </li>\n                            <li class=\"scroll-content-item\">\n                    <a href=\"javascript:void(0);\" class=\"on_fous preview_btn\" data-paper_num=\"8\">\n                        <img src=\"http://file29.mafengwo.net/M00/3B/6E/wKgBpVX362mABBTvAAuoyCSo12801.book.w130.jpeg\" width=\"138\" height=\"195\">\n                        <span>点击<br>预览</span>\n                    </a>\n                </li>\n                            <li class=\"scroll-content-item\">\n                    <a href=\"javascript:void(0);\" class=\"on_fous preview_btn\" data-paper_num=\"9\">\n                        <img src=\"http://file29.mafengwo.net/M00/3B/70/wKgBpVX362mAN2ZGAAv15ZfrtbQ61.book.w130.jpeg\" width=\"138\" height=\"195\">\n                        <span>点击<br>预览</span>\n                    </a>\n                </li>\n                            <li class=\"scroll-content-item\">\n                    <a href=\"javascript:void(0);\" class=\"on_fous preview_btn\" data-paper_num=\"10\">\n                        <img src=\"http://file30.mafengwo.net/M00/3B/71/wKgBpVX362mAf-ByAAqCn4qpkS098.book.w130.jpeg\" width=\"138\" height=\"195\">\n                        <span>点击<br>预览</span>\n                    </a>\n                </li>\n                            <li class=\"scroll-content-item\">\n                    <a href=\"javascript:void(0);\" class=\"on_fous preview_btn\" data-paper_num=\"11\">\n                        <img src=\"http://file29.mafengwo.net/M00/3B/72/wKgBpVX362qAT5XqAAxehhbTL2I71.book.w130.jpeg\" width=\"138\" height=\"195\">\n                        <span>点击<br>预览</span>\n                    </a>\n                </li>\n                            <li class=\"scroll-content-item\">\n                    <a href=\"javascript:void(0);\" class=\"on_fous preview_btn\" data-paper_num=\"12\">\n                        <img src=\"http://file29.mafengwo.net/M00/3B/72/wKgBpVX362qASBcMAAVu_uGx59c95.book.w130.jpeg\" width=\"138\" height=\"195\">\n                        <span>点击<br>预览</span>\n                    </a>\n                </li>"}