{"$category":"crawled","mainimg":"http://file30.mafengwo.net/M00/2A/C1/wKgBpVUdDLmAQZ2gAAuMz3S_G-Q64.book.w230.jpeg","addname":"青岩古镇","tags":"<span>背街</span>\n                    <span>四教并存</span>\n                    <span>青岩猪脚</span>\n                    <span>青岩豆腐</span>\n                <div class=\"clear\"></div>","abstracts":"<p><strong>简介</strong> 古老的石板小路，有些褪色的老式屋子，天井中的坛坛罐罐，置于屋门口的马桶，吆喝着的小贩，伴着小河流水的古桥，幽长的小巷里飘来的阵阵吴语呢哝，这就是青岩古镇，一座静逸的小城。</p>","imgs":"<li class=\"scroll-content-item\">\n                    <a href=\"javascript:void(0);\" class=\"on_fous preview_btn\" data-paper_num=\"0\">\n                        <img src=\"http://file30.mafengwo.net/M00/2A/C1/wKgBpVUdDLmAQZ2gAAuMz3S_G-Q64.book.w130.jpeg\" width=\"138\" height=\"195\">\n                        <span>点击<br>预览</span>\n                    </a>\n                </li>\n                            <li class=\"scroll-content-item\">\n                    <a href=\"javascript:void(0);\" class=\"on_fous preview_btn\" data-paper_num=\"1\">\n                        <img src=\"http://file30.mafengwo.net/M00/2A/C1/wKgBpVUdDLmADomNAAqMkQlyxtc26.book.w130.jpeg\" width=\"138\" height=\"195\">\n                        <span>点击<br>预览</span>\n                    </a>\n                </li>\n                            <li class=\"scroll-content-item\">\n                    <a href=\"javascript:void(0);\" class=\"on_fous preview_btn\" data-paper_num=\"2\">\n                        <img src=\"http://file29.mafengwo.net/M00/2A/C2/wKgBpVUdDLqAYIDQAApm1yIapkU71.book.w130.jpeg\" width=\"138\" height=\"195\">\n                        <span>点击<br>预览</span>\n                    </a>\n                </li>\n                            <li class=\"scroll-content-item\">\n                    <a href=\"javascript:void(0);\" class=\"on_fous preview_btn\" data-paper_num=\"3\">\n                        <img src=\"http://file29.mafengwo.net/M00/2A/C2/wKgBpVUdDLqABT-OAAyuhjnAY2w92.book.w130.jpeg\" width=\"138\" height=\"195\">\n                        <span>点击<br>预览</span>\n                    </a>\n                </li>\n                            <li class=\"scroll-content-item\">\n                    <a href=\"javascript:void(0);\" class=\"on_fous preview_btn\" data-paper_num=\"4\">\n                        <img src=\"http://file29.mafengwo.net/M00/2A/C2/wKgBpVUdDLqANQNVAA2qFs8NVFU66.book.w130.jpeg\" width=\"138\" height=\"195\">\n                        <span>点击<br>预览</span>\n                    </a>\n                </li>\n                            <li class=\"scroll-content-item\">\n                    <a href=\"javascript:void(0);\" class=\"on_fous preview_btn\" data-paper_num=\"5\">\n                        <img src=\"http://file30.mafengwo.net/M00/2A/C3/wKgBpVUdDLqANCXZAA2ACaywYyU96.book.w130.jpeg\" width=\"138\" height=\"195\">\n                        <span>点击<br>预览</span>\n                    </a>\n                </li>\n                            <li class=\"scroll-content-item\">\n                    <a href=\"javascript:void(0);\" class=\"on_fous preview_btn\" data-paper_num=\"6\">\n                        <img src=\"http://file30.mafengwo.net/M00/2A/C3/wKgBpVUdDLqAD8KpAAzoaEgFCa099.book.w130.jpeg\" width=\"138\" height=\"195\">\n                        <span>点击<br>预览</span>\n                    </a>\n                </li>\n                            <li class=\"scroll-content-item\">\n                    <a href=\"javascript:void(0);\" class=\"on_fous preview_btn\" data-paper_num=\"7\">\n                        <img src=\"http://file29.mafengwo.net/M00/2A/C4/wKgBpVUdDLuAcVKlAAtB_PIohAY16.book.w130.jpeg\" width=\"138\" height=\"195\">\n                        <span>点击<br>预览</span>\n                    </a>\n                </li>\n                            <li class=\"scroll-content-item\">\n                    <a href=\"javascript:void(0);\" class=\"on_fous preview_btn\" data-paper_num=\"8\">\n                        <img src=\"http://file29.mafengwo.net/M00/2A/C4/wKgBpVUdDLuAXJEWAAYmT6vjArA17.book.w130.jpeg\" width=\"138\" height=\"195\">\n                        <span>点击<br>预览</span>\n                    </a>\n                </li>"}{"$category":"crawled","mainimg":"http://file30.mafengwo.net/M00/2A/C1/wKgBpVUdDLmAQZ2gAAuMz3S_G-Q64.book.w230.jpeg","addname":"青岩古镇","tags":"<span>背街</span>\n                    <span>四教并存</span>\n                    <span>青岩猪脚</span>\n                    <span>青岩豆腐</span>\n                <div class=\"clear\"></div>","abstracts":"<p><strong>简介</strong> 古老的石板小路，有些褪色的老式屋子，天井中的坛坛罐罐，置于屋门口的马桶，吆喝着的小贩，伴着小河流水的古桥，幽长的小巷里飘来的阵阵吴语呢哝，这就是青岩古镇，一座静逸的小城。</p>","imgs":"<li class=\"scroll-content-item\">\n                    <a href=\"javascript:void(0);\" class=\"on_fous preview_btn\" data-paper_num=\"0\">\n                        <img src=\"http://file30.mafengwo.net/M00/2A/C1/wKgBpVUdDLmAQZ2gAAuMz3S_G-Q64.book.w130.jpeg\" width=\"138\" height=\"195\">\n                        <span>点击<br>预览</span>\n                    </a>\n                </li>\n                            <li class=\"scroll-content-item\">\n                    <a href=\"javascript:void(0);\" class=\"on_fous preview_btn\" data-paper_num=\"1\">\n                        <img src=\"http://file30.mafengwo.net/M00/2A/C1/wKgBpVUdDLmADomNAAqMkQlyxtc26.book.w130.jpeg\" width=\"138\" height=\"195\">\n                        <span>点击<br>预览</span>\n                    </a>\n                </li>\n                            <li class=\"scroll-content-item\">\n                    <a href=\"javascript:void(0);\" class=\"on_fous preview_btn\" data-paper_num=\"2\">\n                        <img src=\"http://file29.mafengwo.net/M00/2A/C2/wKgBpVUdDLqAYIDQAApm1yIapkU71.book.w130.jpeg\" width=\"138\" height=\"195\">\n                        <span>点击<br>预览</span>\n                    </a>\n                </li>\n                            <li class=\"scroll-content-item\">\n                    <a href=\"javascript:void(0);\" class=\"on_fous preview_btn\" data-paper_num=\"3\">\n                        <img src=\"http://file29.mafengwo.net/M00/2A/C2/wKgBpVUdDLqABT-OAAyuhjnAY2w92.book.w130.jpeg\" width=\"138\" height=\"195\">\n                        <span>点击<br>预览</span>\n                    </a>\n                </li>\n                            <li class=\"scroll-content-item\">\n                    <a href=\"javascript:void(0);\" class=\"on_fous preview_btn\" data-paper_num=\"4\">\n                        <img src=\"http://file29.mafengwo.net/M00/2A/C2/wKgBpVUdDLqANQNVAA2qFs8NVFU66.book.w130.jpeg\" width=\"138\" height=\"195\">\n                        <span>点击<br>预览</span>\n                    </a>\n                </li>\n                            <li class=\"scroll-content-item\">\n                    <a href=\"javascript:void(0);\" class=\"on_fous preview_btn\" data-paper_num=\"5\">\n                        <img src=\"http://file30.mafengwo.net/M00/2A/C3/wKgBpVUdDLqANCXZAA2ACaywYyU96.book.w130.jpeg\" width=\"138\" height=\"195\">\n                        <span>点击<br>预览</span>\n                    </a>\n                </li>\n                            <li class=\"scroll-content-item\">\n                    <a href=\"javascript:void(0);\" class=\"on_fous preview_btn\" data-paper_num=\"6\">\n                        <img src=\"http://file30.mafengwo.net/M00/2A/C3/wKgBpVUdDLqAD8KpAAzoaEgFCa099.book.w130.jpeg\" width=\"138\" height=\"195\">\n                        <span>点击<br>预览</span>\n                    </a>\n                </li>\n                            <li class=\"scroll-content-item\">\n                    <a href=\"javascript:void(0);\" class=\"on_fous preview_btn\" data-paper_num=\"7\">\n                        <img src=\"http://file29.mafengwo.net/M00/2A/C4/wKgBpVUdDLuAcVKlAAtB_PIohAY16.book.w130.jpeg\" width=\"138\" height=\"195\">\n                        <span>点击<br>预览</span>\n                    </a>\n                </li>\n                            <li class=\"scroll-content-item\">\n                    <a href=\"javascript:void(0);\" class=\"on_fous preview_btn\" data-paper_num=\"8\">\n                        <img src=\"http://file29.mafengwo.net/M00/2A/C4/wKgBpVUdDLuAXJEWAAYmT6vjArA17.book.w130.jpeg\" width=\"138\" height=\"195\">\n                        <span>点击<br>预览</span>\n                    </a>\n                </li>"}