{"$category":"crawled","mainimg":"http://file29.mafengwo.net/M00/04/BA/wKgBpVWTmYKACZTeAA3_wYSwl4832.book.w230.jpeg","addname":"大叻","tags":"<span>疯狂房子</span>\n                    <span>欧洲情调</span>\n                    <span>滴露咖啡</span>\n                    <span>春香湖</span>\n                    <span>避暑胜地</span>\n                    <span>怀旧小火车</span>\n                <div class=\"clear\"></div>","abstracts":"<p><strong>简介</strong> 大叻是一座非常复古的小城，充满欧式情调。这里风光明媚，四季如春，百花盛开时，如诗如画。在松林的掩映中，偶尔会看到教堂的尖顶，也可以听到有禅意的古庙铃音。这里旧时是法国人酷爱的避暑胜地，在一栋栋的度假屋里，隔着街道，一辆辆的摩托风驰而过，才让人猛然从异国情调中惊醒过来。</p>","imgs":"<li class=\"scroll-content-item\">\n                    <a href=\"javascript:void(0);\" class=\"on_fous preview_btn\" data-paper_num=\"0\">\n                        <img src=\"http://file29.mafengwo.net/M00/04/BA/wKgBpVWTmYKACZTeAA3_wYSwl4832.book.w130.jpeg\" width=\"138\" height=\"195\">\n                        <span>点击<br>预览</span>\n                    </a>\n                </li>\n                            <li class=\"scroll-content-item\">\n                    <a href=\"javascript:void(0);\" class=\"on_fous preview_btn\" data-paper_num=\"1\">\n                        <img src=\"http://file29.mafengwo.net/M00/04/BA/wKgBpVWTmYOARNG_ABAZN8RN96w66.book.w130.jpeg\" width=\"138\" height=\"195\">\n                        <span>点击<br>预览</span>\n                    </a>\n                </li>\n                            <li class=\"scroll-content-item\">\n                    <a href=\"javascript:void(0);\" class=\"on_fous preview_btn\" data-paper_num=\"2\">\n                        <img src=\"http://file29.mafengwo.net/M00/04/BC/wKgBpVWTmYOAWnTDAA93e7KareY18.book.w130.jpeg\" width=\"138\" height=\"195\">\n                        <span>点击<br>预览</span>\n                    </a>\n                </li>\n                            <li class=\"scroll-content-item\">\n                    <a href=\"javascript:void(0);\" class=\"on_fous preview_btn\" data-paper_num=\"3\">\n                        <img src=\"http://file29.mafengwo.net/M00/04/BC/wKgBpVWTmYOAWwL3ABBHcujQAiI55.book.w130.jpeg\" width=\"138\" height=\"195\">\n                        <span>点击<br>预览</span>\n                    </a>\n                </li>\n                            <li class=\"scroll-content-item\">\n                    <a href=\"javascript:void(0);\" class=\"on_fous preview_btn\" data-paper_num=\"4\">\n                        <img src=\"http://file30.mafengwo.net/M00/04/BD/wKgBpVWTmYOAWi1dAA9RbhAP6gw75.book.w130.jpeg\" width=\"138\" height=\"195\">\n                        <span>点击<br>预览</span>\n                    </a>\n                </li>\n                            <li class=\"scroll-content-item\">\n                    <a href=\"javascript:void(0);\" class=\"on_fous preview_btn\" data-paper_num=\"5\">\n                        <img src=\"http://file29.mafengwo.net/M00/04/BE/wKgBpVWTmYSAcUsJAA6JFt8Pgyk33.book.w130.jpeg\" width=\"138\" height=\"195\">\n                        <span>点击<br>预览</span>\n                    </a>\n                </li>\n                            <li class=\"scroll-content-item\">\n                    <a href=\"javascript:void(0);\" class=\"on_fous preview_btn\" data-paper_num=\"6\">\n                        <img src=\"http://file30.mafengwo.net/M00/04/BF/wKgBpVWTmYSANb2YABBryxdN5Ro60.book.w130.jpeg\" width=\"138\" height=\"195\">\n                        <span>点击<br>预览</span>\n                    </a>\n                </li>\n                            <li class=\"scroll-content-item\">\n                    <a href=\"javascript:void(0);\" class=\"on_fous preview_btn\" data-paper_num=\"7\">\n                        <img src=\"http://file30.mafengwo.net/M00/04/BF/wKgBpVWTmYSAXA0gAA90ZLC9Eeg42.book.w130.jpeg\" width=\"138\" height=\"195\">\n                        <span>点击<br>预览</span>\n                    </a>\n                </li>\n                            <li class=\"scroll-content-item\">\n                    <a href=\"javascript:void(0);\" class=\"on_fous preview_btn\" data-paper_num=\"8\">\n                        <img src=\"http://file29.mafengwo.net/M00/04/C0/wKgBpVWTmYSALNzIAA6Ns0AhS6484.book.w130.jpeg\" width=\"138\" height=\"195\">\n                        <span>点击<br>预览</span>\n                    </a>\n                </li>\n                            <li class=\"scroll-content-item\">\n                    <a href=\"javascript:void(0);\" class=\"on_fous preview_btn\" data-paper_num=\"9\">\n                        <img src=\"http://file30.mafengwo.net/M00/04/C1/wKgBpVWTmYWAXNhlABAeApYXTUE18.book.w130.jpeg\" width=\"138\" height=\"195\">\n                        <span>点击<br>预览</span>\n                    </a>\n                </li>\n                            <li class=\"scroll-content-item\">\n                    <a href=\"javascript:void(0);\" class=\"on_fous preview_btn\" data-paper_num=\"10\">\n                        <img src=\"http://file29.mafengwo.net/M00/04/C2/wKgBpVWTmYWAXchqAA2bEjnTf6o61.book.w130.jpeg\" width=\"138\" height=\"195\">\n                        <span>点击<br>预览</span>\n                    </a>\n                </li>\n                            <li class=\"scroll-content-item\">\n                    <a href=\"javascript:void(0);\" class=\"on_fous preview_btn\" data-paper_num=\"11\">\n                        <img src=\"http://file30.mafengwo.net/M00/04/C3/wKgBpVWTmYWAeDp-AA2R6xe2vNs42.book.w130.jpeg\" width=\"138\" height=\"195\">\n                        <span>点击<br>预览</span>\n                    </a>\n                </li>\n                            <li class=\"scroll-content-item\">\n                    <a href=\"javascript:void(0);\" class=\"on_fous preview_btn\" data-paper_num=\"12\">\n                        <img src=\"http://file29.mafengwo.net/M00/04/C4/wKgBpVWTmYaAC2PPAAxuNsFagEE17.book.w130.jpeg\" width=\"138\" height=\"195\">\n                        <span>点击<br>预览</span>\n                    </a>\n                </li>\n                            <li class=\"scroll-content-item\">\n                    <a href=\"javascript:void(0);\" class=\"on_fous preview_btn\" data-paper_num=\"13\">\n                        <img src=\"http://file29.mafengwo.net/M00/04/C6/wKgBpVWTmYaAZnrcAA3eGZj2DXo47.book.w130.jpeg\" width=\"138\" height=\"195\">\n                        <span>点击<br>预览</span>\n                    </a>\n                </li>\n                            <li class=\"scroll-content-item\">\n                    <a href=\"javascript:void(0);\" class=\"on_fous preview_btn\" data-paper_num=\"14\">\n                        <img src=\"http://file29.mafengwo.net/M00/04/C6/wKgBpVWTmYeAd4ISAAjGTfcbet802.book.w130.jpeg\" width=\"138\" height=\"195\">\n                        <span>点击<br>预览</span>\n                    </a>\n                </li>"}{"$category":"crawled","mainimg":"http://file29.mafengwo.net/M00/04/BA/wKgBpVWTmYKACZTeAA3_wYSwl4832.book.w230.jpeg","addname":"大叻","tags":"<span>疯狂房子</span>\n                    <span>欧洲情调</span>\n                    <span>滴露咖啡</span>\n                    <span>春香湖</span>\n                    <span>避暑胜地</span>\n                    <span>怀旧小火车</span>\n                <div class=\"clear\"></div>","abstracts":"<p><strong>简介</strong> 大叻是一座非常复古的小城，充满欧式情调。这里风光明媚，四季如春，百花盛开时，如诗如画。在松林的掩映中，偶尔会看到教堂的尖顶，也可以听到有禅意的古庙铃音。这里旧时是法国人酷爱的避暑胜地，在一栋栋的度假屋里，隔着街道，一辆辆的摩托风驰而过，才让人猛然从异国情调中惊醒过来。</p>","imgs":"<li class=\"scroll-content-item\">\n                    <a href=\"javascript:void(0);\" class=\"on_fous preview_btn\" data-paper_num=\"0\">\n                        <img src=\"http://file29.mafengwo.net/M00/04/BA/wKgBpVWTmYKACZTeAA3_wYSwl4832.book.w130.jpeg\" width=\"138\" height=\"195\">\n                        <span>点击<br>预览</span>\n                    </a>\n                </li>\n                            <li class=\"scroll-content-item\">\n                    <a href=\"javascript:void(0);\" class=\"on_fous preview_btn\" data-paper_num=\"1\">\n                        <img src=\"http://file29.mafengwo.net/M00/04/BA/wKgBpVWTmYOARNG_ABAZN8RN96w66.book.w130.jpeg\" width=\"138\" height=\"195\">\n                        <span>点击<br>预览</span>\n                    </a>\n                </li>\n                            <li class=\"scroll-content-item\">\n                    <a href=\"javascript:void(0);\" class=\"on_fous preview_btn\" data-paper_num=\"2\">\n                        <img src=\"http://file29.mafengwo.net/M00/04/BC/wKgBpVWTmYOAWnTDAA93e7KareY18.book.w130.jpeg\" width=\"138\" height=\"195\">\n                        <span>点击<br>预览</span>\n                    </a>\n                </li>\n                            <li class=\"scroll-content-item\">\n                    <a href=\"javascript:void(0);\" class=\"on_fous preview_btn\" data-paper_num=\"3\">\n                        <img src=\"http://file29.mafengwo.net/M00/04/BC/wKgBpVWTmYOAWwL3ABBHcujQAiI55.book.w130.jpeg\" width=\"138\" height=\"195\">\n                        <span>点击<br>预览</span>\n                    </a>\n                </li>\n                            <li class=\"scroll-content-item\">\n                    <a href=\"javascript:void(0);\" class=\"on_fous preview_btn\" data-paper_num=\"4\">\n                        <img src=\"http://file30.mafengwo.net/M00/04/BD/wKgBpVWTmYOAWi1dAA9RbhAP6gw75.book.w130.jpeg\" width=\"138\" height=\"195\">\n                        <span>点击<br>预览</span>\n                    </a>\n                </li>\n                            <li class=\"scroll-content-item\">\n                    <a href=\"javascript:void(0);\" class=\"on_fous preview_btn\" data-paper_num=\"5\">\n                        <img src=\"http://file29.mafengwo.net/M00/04/BE/wKgBpVWTmYSAcUsJAA6JFt8Pgyk33.book.w130.jpeg\" width=\"138\" height=\"195\">\n                        <span>点击<br>预览</span>\n                    </a>\n                </li>\n                            <li class=\"scroll-content-item\">\n                    <a href=\"javascript:void(0);\" class=\"on_fous preview_btn\" data-paper_num=\"6\">\n                        <img src=\"http://file30.mafengwo.net/M00/04/BF/wKgBpVWTmYSANb2YABBryxdN5Ro60.book.w130.jpeg\" width=\"138\" height=\"195\">\n                        <span>点击<br>预览</span>\n                    </a>\n                </li>\n                            <li class=\"scroll-content-item\">\n                    <a href=\"javascript:void(0);\" class=\"on_fous preview_btn\" data-paper_num=\"7\">\n                        <img src=\"http://file30.mafengwo.net/M00/04/BF/wKgBpVWTmYSAXA0gAA90ZLC9Eeg42.book.w130.jpeg\" width=\"138\" height=\"195\">\n                        <span>点击<br>预览</span>\n                    </a>\n                </li>\n                            <li class=\"scroll-content-item\">\n                    <a href=\"javascript:void(0);\" class=\"on_fous preview_btn\" data-paper_num=\"8\">\n                        <img src=\"http://file29.mafengwo.net/M00/04/C0/wKgBpVWTmYSALNzIAA6Ns0AhS6484.book.w130.jpeg\" width=\"138\" height=\"195\">\n                        <span>点击<br>预览</span>\n                    </a>\n                </li>\n                            <li class=\"scroll-content-item\">\n                    <a href=\"javascript:void(0);\" class=\"on_fous preview_btn\" data-paper_num=\"9\">\n                        <img src=\"http://file30.mafengwo.net/M00/04/C1/wKgBpVWTmYWAXNhlABAeApYXTUE18.book.w130.jpeg\" width=\"138\" height=\"195\">\n                        <span>点击<br>预览</span>\n                    </a>\n                </li>\n                            <li class=\"scroll-content-item\">\n                    <a href=\"javascript:void(0);\" class=\"on_fous preview_btn\" data-paper_num=\"10\">\n                        <img src=\"http://file29.mafengwo.net/M00/04/C2/wKgBpVWTmYWAXchqAA2bEjnTf6o61.book.w130.jpeg\" width=\"138\" height=\"195\">\n                        <span>点击<br>预览</span>\n                    </a>\n                </li>\n                            <li class=\"scroll-content-item\">\n                    <a href=\"javascript:void(0);\" class=\"on_fous preview_btn\" data-paper_num=\"11\">\n                        <img src=\"http://file30.mafengwo.net/M00/04/C3/wKgBpVWTmYWAeDp-AA2R6xe2vNs42.book.w130.jpeg\" width=\"138\" height=\"195\">\n                        <span>点击<br>预览</span>\n                    </a>\n                </li>\n                            <li class=\"scroll-content-item\">\n                    <a href=\"javascript:void(0);\" class=\"on_fous preview_btn\" data-paper_num=\"12\">\n                        <img src=\"http://file29.mafengwo.net/M00/04/C4/wKgBpVWTmYaAC2PPAAxuNsFagEE17.book.w130.jpeg\" width=\"138\" height=\"195\">\n                        <span>点击<br>预览</span>\n                    </a>\n                </li>\n                            <li class=\"scroll-content-item\">\n                    <a href=\"javascript:void(0);\" class=\"on_fous preview_btn\" data-paper_num=\"13\">\n                        <img src=\"http://file29.mafengwo.net/M00/04/C6/wKgBpVWTmYaAZnrcAA3eGZj2DXo47.book.w130.jpeg\" width=\"138\" height=\"195\">\n                        <span>点击<br>预览</span>\n                    </a>\n                </li>\n                            <li class=\"scroll-content-item\">\n                    <a href=\"javascript:void(0);\" class=\"on_fous preview_btn\" data-paper_num=\"14\">\n                        <img src=\"http://file29.mafengwo.net/M00/04/C6/wKgBpVWTmYeAd4ISAAjGTfcbet802.book.w130.jpeg\" width=\"138\" height=\"195\">\n                        <span>点击<br>预览</span>\n                    </a>\n                </li>"}