{"$category":"crawled","mainimg":"http://file30.mafengwo.net/M00/C4/F3/wKgBpVWb-ieAZga1AAhPFAMoAeg63.book.w230.jpeg","addname":"意大利","tags":"<span>米开朗基罗</span>\n                    <span>大卫像</span>\n                    <span>古罗马</span>\n                    <span>时尚米兰</span>\n                    <span>水城威尼斯</span>\n                <div class=\"clear\"></div>","abstracts":"<p><strong>简介</strong> 显赫一时的古罗马帝国、庞贝古城、比萨斜塔、佛罗伦萨、风光旖旎的水城威尼斯、被誉为世界第八大奇迹的古罗马竞技场、疯狂的足球比赛、米兰时尚的气息、极富魅力的雕塑般完美的男人和女人，意大利独特的城市风貌，优美的自然风光，灿烂的历史和文化，一直是旅行者们心醉不已的梦想之地。</p>","imgs":"<li class=\"scroll-content-item\">\n                    <a href=\"javascript:void(0);\" class=\"on_fous preview_btn\" data-paper_num=\"0\">\n                        <img src=\"http://file30.mafengwo.net/M00/C4/F3/wKgBpVWb-ieAZga1AAhPFAMoAeg63.book.w130.jpeg\" width=\"138\" height=\"195\">\n                        <span>点击<br>预览</span>\n                    </a>\n                </li>\n                            <li class=\"scroll-content-item\">\n                    <a href=\"javascript:void(0);\" class=\"on_fous preview_btn\" data-paper_num=\"1\">\n                        <img src=\"http://file29.mafengwo.net/M00/C4/F4/wKgBpVWb-iiABJfXAAsT1TyzJNg24.book.w130.jpeg\" width=\"138\" height=\"195\">\n                        <span>点击<br>预览</span>\n                    </a>\n                </li>\n                            <li class=\"scroll-content-item\">\n                    <a href=\"javascript:void(0);\" class=\"on_fous preview_btn\" data-paper_num=\"2\">\n                        <img src=\"http://file30.mafengwo.net/M00/C4/F5/wKgBpVWb-iiAC1VKAAvbT4I5YdI96.book.w130.jpeg\" width=\"138\" height=\"195\">\n                        <span>点击<br>预览</span>\n                    </a>\n                </li>\n                            <li class=\"scroll-content-item\">\n                    <a href=\"javascript:void(0);\" class=\"on_fous preview_btn\" data-paper_num=\"3\">\n                        <img src=\"http://file29.mafengwo.net/M00/C4/F6/wKgBpVWb-iiAOoIjAAwrBsOek7M61.book.w130.jpeg\" width=\"138\" height=\"195\">\n                        <span>点击<br>预览</span>\n                    </a>\n                </li>\n                            <li class=\"scroll-content-item\">\n                    <a href=\"javascript:void(0);\" class=\"on_fous preview_btn\" data-paper_num=\"4\">\n                        <img src=\"http://file30.mafengwo.net/M00/C4/F9/wKgBpVWb-imAcZxRAAuPDXBqHZg05.book.w130.jpeg\" width=\"138\" height=\"195\">\n                        <span>点击<br>预览</span>\n                    </a>\n                </li>\n                            <li class=\"scroll-content-item\">\n                    <a href=\"javascript:void(0);\" class=\"on_fous preview_btn\" data-paper_num=\"5\">\n                        <img src=\"http://file29.mafengwo.net/M00/C4/FA/wKgBpVWb-imAMdxVAA31Uymzleo37.book.w130.jpeg\" width=\"138\" height=\"195\">\n                        <span>点击<br>预览</span>\n                    </a>\n                </li>\n                            <li class=\"scroll-content-item\">\n                    <a href=\"javascript:void(0);\" class=\"on_fous preview_btn\" data-paper_num=\"6\">\n                        <img src=\"http://file30.mafengwo.net/M00/C4/FB/wKgBpVWb-imAU2PdAA5n9UqmA_E78.book.w130.jpeg\" width=\"138\" height=\"195\">\n                        <span>点击<br>预览</span>\n                    </a>\n                </li>\n                            <li class=\"scroll-content-item\">\n                    <a href=\"javascript:void(0);\" class=\"on_fous preview_btn\" data-paper_num=\"7\">\n                        <img src=\"http://file29.mafengwo.net/M00/C4/FC/wKgBpVWb-imASEUUAAvCB0DEMVY57.book.w130.jpeg\" width=\"138\" height=\"195\">\n                        <span>点击<br>预览</span>\n                    </a>\n                </li>\n                            <li class=\"scroll-content-item\">\n                    <a href=\"javascript:void(0);\" class=\"on_fous preview_btn\" data-paper_num=\"8\">\n                        <img src=\"http://file30.mafengwo.net/M00/C4/FD/wKgBpVWb-iqAAyO3AAvtL8MpD1450.book.w130.jpeg\" width=\"138\" height=\"195\">\n                        <span>点击<br>预览</span>\n                    </a>\n                </li>\n                            <li class=\"scroll-content-item\">\n                    <a href=\"javascript:void(0);\" class=\"on_fous preview_btn\" data-paper_num=\"9\">\n                        <img src=\"http://file29.mafengwo.net/M00/C4/FE/wKgBpVWb-iqABdoTAAr6I-9zUBY37.book.w130.jpeg\" width=\"138\" height=\"195\">\n                        <span>点击<br>预览</span>\n                    </a>\n                </li>\n                            <li class=\"scroll-content-item\">\n                    <a href=\"javascript:void(0);\" class=\"on_fous preview_btn\" data-paper_num=\"10\">\n                        <img src=\"http://file29.mafengwo.net/M00/C5/00/wKgBpVWb-iqANRyTAAzN_O_Z9p407.book.w130.jpeg\" width=\"138\" height=\"195\">\n                        <span>点击<br>预览</span>\n                    </a>\n                </li>\n                            <li class=\"scroll-content-item\">\n                    <a href=\"javascript:void(0);\" class=\"on_fous preview_btn\" data-paper_num=\"11\">\n                        <img src=\"http://file30.mafengwo.net/M00/C5/01/wKgBpVWb-iqATXkoAApzJIyUvh433.book.w130.jpeg\" width=\"138\" height=\"195\">\n                        <span>点击<br>预览</span>\n                    </a>\n                </li>\n                            <li class=\"scroll-content-item\">\n                    <a href=\"javascript:void(0);\" class=\"on_fous preview_btn\" data-paper_num=\"12\">\n                        <img src=\"http://file29.mafengwo.net/M00/C5/02/wKgBpVWb-iuAd2bbAAqNUjvO0ec69.book.w130.jpeg\" width=\"138\" height=\"195\">\n                        <span>点击<br>预览</span>\n                    </a>\n                </li>\n                            <li class=\"scroll-content-item\">\n                    <a href=\"javascript:void(0);\" class=\"on_fous preview_btn\" data-paper_num=\"13\">\n                        <img src=\"http://file30.mafengwo.net/M00/C5/03/wKgBpVWb-iuAQnOuAAq-qq53wLE47.book.w130.jpeg\" width=\"138\" height=\"195\">\n                        <span>点击<br>预览</span>\n                    </a>\n                </li>\n                            <li class=\"scroll-content-item\">\n                    <a href=\"javascript:void(0);\" class=\"on_fous preview_btn\" data-paper_num=\"14\">\n                        <img src=\"http://file29.mafengwo.net/M00/C5/04/wKgBpVWb-iuAfgPNAAs1ie_73SI93.book.w130.jpeg\" width=\"138\" height=\"195\">\n                        <span>点击<br>预览</span>\n                    </a>\n                </li>\n                            <li class=\"scroll-content-item\">\n                    <a href=\"javascript:void(0);\" class=\"on_fous preview_btn\" data-paper_num=\"15\">\n                        <img src=\"http://file30.mafengwo.net/M00/C5/05/wKgBpVWb-iuAWLJ-AAxJRjKQu4I25.book.w130.jpeg\" width=\"138\" height=\"195\">\n                        <span>点击<br>预览</span>\n                    </a>\n                </li>\n                            <li class=\"scroll-content-item\">\n                    <a href=\"javascript:void(0);\" class=\"on_fous preview_btn\" data-paper_num=\"16\">\n                        <img src=\"http://file30.mafengwo.net/M00/C5/05/wKgBpVWb-iyAZcTDAAy4x-u6Rgs42.book.w130.jpeg\" width=\"138\" height=\"195\">\n                        <span>点击<br>预览</span>\n                    </a>\n                </li>\n                            <li class=\"scroll-content-item\">\n                    <a href=\"javascript:void(0);\" class=\"on_fous preview_btn\" data-paper_num=\"17\">\n                        <img src=\"http://file30.mafengwo.net/M00/C5/07/wKgBpVWb-iyAZLQTAAyycMAoJSQ30.book.w130.jpeg\" width=\"138\" height=\"195\">\n                        <span>点击<br>预览</span>\n                    </a>\n                </li>\n                            <li class=\"scroll-content-item\">\n                    <a href=\"javascript:void(0);\" class=\"on_fous preview_btn\" data-paper_num=\"18\">\n                        <img src=\"http://file29.mafengwo.net/M00/C5/08/wKgBpVWb-iyAMt2KAA0UOT8UGUA42.book.w130.jpeg\" width=\"138\" height=\"195\">\n                        <span>点击<br>预览</span>\n                    </a>\n                </li>\n                            <li class=\"scroll-content-item\">\n                    <a href=\"javascript:void(0);\" class=\"on_fous preview_btn\" data-paper_num=\"19\">\n                        <img src=\"http://file30.mafengwo.net/M00/C5/09/wKgBpVWb-i2AaWqbAArKJP91iRY38.book.w130.jpeg\" width=\"138\" height=\"195\">\n                        <span>点击<br>预览</span>\n                    </a>\n                </li>\n                            <li class=\"scroll-content-item\">\n                    <a href=\"javascript:void(0);\" class=\"on_fous preview_btn\" data-paper_num=\"20\">\n                        <img src=\"http://file29.mafengwo.net/M00/C5/0A/wKgBpVWb-i2ALAokAAxm28el51M58.book.w130.jpeg\" width=\"138\" height=\"195\">\n                        <span>点击<br>预览</span>\n                    </a>\n                </li>\n                            <li class=\"scroll-content-item\">\n                    <a href=\"javascript:void(0);\" class=\"on_fous preview_btn\" data-paper_num=\"21\">\n                        <img src=\"http://file30.mafengwo.net/M00/C5/0B/wKgBpVWb-i2AT4wUAAygqXJoZr003.book.w130.jpeg\" width=\"138\" height=\"195\">\n                        <span>点击<br>预览</span>\n                    </a>\n                </li>\n                            <li class=\"scroll-content-item\">\n                    <a href=\"javascript:void(0);\" class=\"on_fous preview_btn\" data-paper_num=\"22\">\n                        <img src=\"http://file29.mafengwo.net/M00/C5/0C/wKgBpVWb-i2AeKpQAA1KZ1NHJDs00.book.w130.jpeg\" width=\"138\" height=\"195\">\n                        <span>点击<br>预览</span>\n                    </a>\n                </li>\n                            <li class=\"scroll-content-item\">\n                    <a href=\"javascript:void(0);\" class=\"on_fous preview_btn\" data-paper_num=\"23\">\n                        <img src=\"http://file29.mafengwo.net/M00/C5/0C/wKgBpVWb-i6Ad9GcAAzTX5t6cUA32.book.w130.jpeg\" width=\"138\" height=\"195\">\n                        <span>点击<br>预览</span>\n                    </a>\n                </li>\n                            <li class=\"scroll-content-item\">\n                    <a href=\"javascript:void(0);\" class=\"on_fous preview_btn\" data-paper_num=\"24\">\n                        <img src=\"http://file30.mafengwo.net/M00/C5/0D/wKgBpVWb-i6AL0I_AArPsunQkPo08.book.w130.jpeg\" width=\"138\" height=\"195\">\n                        <span>点击<br>预览</span>\n                    </a>\n                </li>\n                            <li class=\"scroll-content-item\">\n                    <a href=\"javascript:void(0);\" class=\"on_fous preview_btn\" data-paper_num=\"25\">\n                        <img src=\"http://file29.mafengwo.net/M00/C5/0E/wKgBpVWb-i6AfjEuAAzeEpK5bas21.book.w130.jpeg\" width=\"138\" height=\"195\">\n                        <span>点击<br>预览</span>\n                    </a>\n                </li>\n                            <li class=\"scroll-content-item\">\n                    <a href=\"javascript:void(0);\" class=\"on_fous preview_btn\" data-paper_num=\"26\">\n                        <img src=\"http://file30.mafengwo.net/M00/C5/0F/wKgBpVWb-i6AJ33NAAqaNjn_vEg29.book.w130.jpeg\" width=\"138\" height=\"195\">\n                        <span>点击<br>预览</span>\n                    </a>\n                </li>\n                            <li class=\"scroll-content-item\">\n                    <a href=\"javascript:void(0);\" class=\"on_fous preview_btn\" data-paper_num=\"27\">\n                        <img src=\"http://file29.mafengwo.net/M00/C5/10/wKgBpVWb-i-AfEIyAAvCQUR_7r848.book.w130.jpeg\" width=\"138\" height=\"195\">\n                        <span>点击<br>预览</span>\n                    </a>\n                </li>\n                            <li class=\"scroll-content-item\">\n                    <a href=\"javascript:void(0);\" class=\"on_fous preview_btn\" data-paper_num=\"28\">\n                        <img src=\"http://file30.mafengwo.net/M00/C5/11/wKgBpVWb-i-ALL3dAAsmiadrC2480.book.w130.jpeg\" width=\"138\" height=\"195\">\n                        <span>点击<br>预览</span>\n                    </a>\n                </li>\n                            <li class=\"scroll-content-item\">\n                    <a href=\"javascript:void(0);\" class=\"on_fous preview_btn\" data-paper_num=\"29\">\n                        <img src=\"http://file30.mafengwo.net/M00/C5/11/wKgBpVWb-i-AUo_5AApgd_EOdvA16.book.w130.jpeg\" width=\"138\" height=\"195\">\n                        <span>点击<br>预览</span>\n                    </a>\n                </li>\n                            <li class=\"scroll-content-item\">\n                    <a href=\"javascript:void(0);\" class=\"on_fous preview_btn\" data-paper_num=\"30\">\n                        <img src=\"http://file29.mafengwo.net/M00/C5/12/wKgBpVWb-i-ACmMJAA1JD2M4K9075.book.w130.jpeg\" width=\"138\" height=\"195\">\n                        <span>点击<br>预览</span>\n                    </a>\n                </li>\n                            <li class=\"scroll-content-item\">\n                    <a href=\"javascript:void(0);\" class=\"on_fous preview_btn\" data-paper_num=\"31\">\n                        <img src=\"http://file30.mafengwo.net/M00/C5/13/wKgBpVWb-jCATLurAAqkIj_Bl4w13.book.w130.jpeg\" width=\"138\" height=\"195\">\n                        <span>点击<br>预览</span>\n                    </a>\n                </li>\n                            <li class=\"scroll-content-item\">\n                    <a href=\"javascript:void(0);\" class=\"on_fous preview_btn\" data-paper_num=\"32\">\n                        <img src=\"http://file29.mafengwo.net/M00/C5/14/wKgBpVWb-jCAEzRQAAp6NdkQKgA66.book.w130.jpeg\" width=\"138\" height=\"195\">\n                        <span>点击<br>预览</span>\n                    </a>\n                </li>\n                            <li class=\"scroll-content-item\">\n                    <a href=\"javascript:void(0);\" class=\"on_fous preview_btn\" data-paper_num=\"33\">\n                        <img src=\"http://file30.mafengwo.net/M00/C5/15/wKgBpVWb-jCAO9GBAAmy_LHkVuk48.book.w130.jpeg\" width=\"138\" height=\"195\">\n                        <span>点击<br>预览</span>\n                    </a>\n                </li>\n                            <li class=\"scroll-content-item\">\n                    <a href=\"javascript:void(0);\" class=\"on_fous preview_btn\" data-paper_num=\"34\">\n                        <img src=\"http://file30.mafengwo.net/M00/C5/17/wKgBpVWb-jGAJTmQAAtj0w55hks12.book.w130.jpeg\" width=\"138\" height=\"195\">\n                        <span>点击<br>预览</span>\n                    </a>\n                </li>\n                            <li class=\"scroll-content-item\">\n                    <a href=\"javascript:void(0);\" class=\"on_fous preview_btn\" data-paper_num=\"35\">\n                        <img src=\"http://file30.mafengwo.net/M00/C5/17/wKgBpVWb-jGAM96VAAu0YKw1BHU88.book.w130.jpeg\" width=\"138\" height=\"195\">\n                        <span>点击<br>预览</span>\n                    </a>\n                </li>\n                            <li class=\"scroll-content-item\">\n                    <a href=\"javascript:void(0);\" class=\"on_fous preview_btn\" data-paper_num=\"36\">\n                        <img src=\"http://file29.mafengwo.net/M00/C5/18/wKgBpVWb-jGAVE3FAAqduMn8Olg68.book.w130.jpeg\" width=\"138\" height=\"195\">\n                        <span>点击<br>预览</span>\n                    </a>\n                </li>\n                            <li class=\"scroll-content-item\">\n                    <a href=\"javascript:void(0);\" class=\"on_fous preview_btn\" data-paper_num=\"37\">\n                        <img src=\"http://file30.mafengwo.net/M00/C5/19/wKgBpVWb-jGAJFB0AAp0V7xypYY25.book.w130.jpeg\" width=\"138\" height=\"195\">\n                        <span>点击<br>预览</span>\n                    </a>\n                </li>\n                            <li class=\"scroll-content-item\">\n                    <a href=\"javascript:void(0);\" class=\"on_fous preview_btn\" data-paper_num=\"38\">\n                        <img src=\"http://file29.mafengwo.net/M00/C5/1A/wKgBpVWb-jKALcxeAAmUo-SVZzI26.book.w130.jpeg\" width=\"138\" height=\"195\">\n                        <span>点击<br>预览</span>\n                    </a>\n                </li>"}{"$category":"crawled","mainimg":"http://file30.mafengwo.net/M00/C4/F3/wKgBpVWb-ieAZga1AAhPFAMoAeg63.book.w230.jpeg","addname":"意大利","tags":"<span>米开朗基罗</span>\n                    <span>大卫像</span>\n                    <span>古罗马</span>\n                    <span>时尚米兰</span>\n                    <span>水城威尼斯</span>\n                <div class=\"clear\"></div>","abstracts":"<p><strong>简介</strong> 显赫一时的古罗马帝国、庞贝古城、比萨斜塔、佛罗伦萨、风光旖旎的水城威尼斯、被誉为世界第八大奇迹的古罗马竞技场、疯狂的足球比赛、米兰时尚的气息、极富魅力的雕塑般完美的男人和女人，意大利独特的城市风貌，优美的自然风光，灿烂的历史和文化，一直是旅行者们心醉不已的梦想之地。</p>","imgs":"<li class=\"scroll-content-item\">\n                    <a href=\"javascript:void(0);\" class=\"on_fous preview_btn\" data-paper_num=\"0\">\n                        <img src=\"http://file30.mafengwo.net/M00/C4/F3/wKgBpVWb-ieAZga1AAhPFAMoAeg63.book.w130.jpeg\" width=\"138\" height=\"195\">\n                        <span>点击<br>预览</span>\n                    </a>\n                </li>\n                            <li class=\"scroll-content-item\">\n                    <a href=\"javascript:void(0);\" class=\"on_fous preview_btn\" data-paper_num=\"1\">\n                        <img src=\"http://file29.mafengwo.net/M00/C4/F4/wKgBpVWb-iiABJfXAAsT1TyzJNg24.book.w130.jpeg\" width=\"138\" height=\"195\">\n                        <span>点击<br>预览</span>\n                    </a>\n                </li>\n                            <li class=\"scroll-content-item\">\n                    <a href=\"javascript:void(0);\" class=\"on_fous preview_btn\" data-paper_num=\"2\">\n                        <img src=\"http://file30.mafengwo.net/M00/C4/F5/wKgBpVWb-iiAC1VKAAvbT4I5YdI96.book.w130.jpeg\" width=\"138\" height=\"195\">\n                        <span>点击<br>预览</span>\n                    </a>\n                </li>\n                            <li class=\"scroll-content-item\">\n                    <a href=\"javascript:void(0);\" class=\"on_fous preview_btn\" data-paper_num=\"3\">\n                        <img src=\"http://file29.mafengwo.net/M00/C4/F6/wKgBpVWb-iiAOoIjAAwrBsOek7M61.book.w130.jpeg\" width=\"138\" height=\"195\">\n                        <span>点击<br>预览</span>\n                    </a>\n                </li>\n                            <li class=\"scroll-content-item\">\n                    <a href=\"javascript:void(0);\" class=\"on_fous preview_btn\" data-paper_num=\"4\">\n                        <img src=\"http://file30.mafengwo.net/M00/C4/F9/wKgBpVWb-imAcZxRAAuPDXBqHZg05.book.w130.jpeg\" width=\"138\" height=\"195\">\n                        <span>点击<br>预览</span>\n                    </a>\n                </li>\n                            <li class=\"scroll-content-item\">\n                    <a href=\"javascript:void(0);\" class=\"on_fous preview_btn\" data-paper_num=\"5\">\n                        <img src=\"http://file29.mafengwo.net/M00/C4/FA/wKgBpVWb-imAMdxVAA31Uymzleo37.book.w130.jpeg\" width=\"138\" height=\"195\">\n                        <span>点击<br>预览</span>\n                    </a>\n                </li>\n                            <li class=\"scroll-content-item\">\n                    <a href=\"javascript:void(0);\" class=\"on_fous preview_btn\" data-paper_num=\"6\">\n                        <img src=\"http://file30.mafengwo.net/M00/C4/FB/wKgBpVWb-imAU2PdAA5n9UqmA_E78.book.w130.jpeg\" width=\"138\" height=\"195\">\n                        <span>点击<br>预览</span>\n                    </a>\n                </li>\n                            <li class=\"scroll-content-item\">\n                    <a href=\"javascript:void(0);\" class=\"on_fous preview_btn\" data-paper_num=\"7\">\n                        <img src=\"http://file29.mafengwo.net/M00/C4/FC/wKgBpVWb-imASEUUAAvCB0DEMVY57.book.w130.jpeg\" width=\"138\" height=\"195\">\n                        <span>点击<br>预览</span>\n                    </a>\n                </li>\n                            <li class=\"scroll-content-item\">\n                    <a href=\"javascript:void(0);\" class=\"on_fous preview_btn\" data-paper_num=\"8\">\n                        <img src=\"http://file30.mafengwo.net/M00/C4/FD/wKgBpVWb-iqAAyO3AAvtL8MpD1450.book.w130.jpeg\" width=\"138\" height=\"195\">\n                        <span>点击<br>预览</span>\n                    </a>\n                </li>\n                            <li class=\"scroll-content-item\">\n                    <a href=\"javascript:void(0);\" class=\"on_fous preview_btn\" data-paper_num=\"9\">\n                        <img src=\"http://file29.mafengwo.net/M00/C4/FE/wKgBpVWb-iqABdoTAAr6I-9zUBY37.book.w130.jpeg\" width=\"138\" height=\"195\">\n                        <span>点击<br>预览</span>\n                    </a>\n                </li>\n                            <li class=\"scroll-content-item\">\n                    <a href=\"javascript:void(0);\" class=\"on_fous preview_btn\" data-paper_num=\"10\">\n                        <img src=\"http://file29.mafengwo.net/M00/C5/00/wKgBpVWb-iqANRyTAAzN_O_Z9p407.book.w130.jpeg\" width=\"138\" height=\"195\">\n                        <span>点击<br>预览</span>\n                    </a>\n                </li>\n                            <li class=\"scroll-content-item\">\n                    <a href=\"javascript:void(0);\" class=\"on_fous preview_btn\" data-paper_num=\"11\">\n                        <img src=\"http://file30.mafengwo.net/M00/C5/01/wKgBpVWb-iqATXkoAApzJIyUvh433.book.w130.jpeg\" width=\"138\" height=\"195\">\n                        <span>点击<br>预览</span>\n                    </a>\n                </li>\n                            <li class=\"scroll-content-item\">\n                    <a href=\"javascript:void(0);\" class=\"on_fous preview_btn\" data-paper_num=\"12\">\n                        <img src=\"http://file29.mafengwo.net/M00/C5/02/wKgBpVWb-iuAd2bbAAqNUjvO0ec69.book.w130.jpeg\" width=\"138\" height=\"195\">\n                        <span>点击<br>预览</span>\n                    </a>\n                </li>\n                            <li class=\"scroll-content-item\">\n                    <a href=\"javascript:void(0);\" class=\"on_fous preview_btn\" data-paper_num=\"13\">\n                        <img src=\"http://file30.mafengwo.net/M00/C5/03/wKgBpVWb-iuAQnOuAAq-qq53wLE47.book.w130.jpeg\" width=\"138\" height=\"195\">\n                        <span>点击<br>预览</span>\n                    </a>\n                </li>\n                            <li class=\"scroll-content-item\">\n                    <a href=\"javascript:void(0);\" class=\"on_fous preview_btn\" data-paper_num=\"14\">\n                        <img src=\"http://file29.mafengwo.net/M00/C5/04/wKgBpVWb-iuAfgPNAAs1ie_73SI93.book.w130.jpeg\" width=\"138\" height=\"195\">\n                        <span>点击<br>预览</span>\n                    </a>\n                </li>\n                            <li class=\"scroll-content-item\">\n                    <a href=\"javascript:void(0);\" class=\"on_fous preview_btn\" data-paper_num=\"15\">\n                        <img src=\"http://file30.mafengwo.net/M00/C5/05/wKgBpVWb-iuAWLJ-AAxJRjKQu4I25.book.w130.jpeg\" width=\"138\" height=\"195\">\n                        <span>点击<br>预览</span>\n                    </a>\n                </li>\n                            <li class=\"scroll-content-item\">\n                    <a href=\"javascript:void(0);\" class=\"on_fous preview_btn\" data-paper_num=\"16\">\n                        <img src=\"http://file30.mafengwo.net/M00/C5/05/wKgBpVWb-iyAZcTDAAy4x-u6Rgs42.book.w130.jpeg\" width=\"138\" height=\"195\">\n                        <span>点击<br>预览</span>\n                    </a>\n                </li>\n                            <li class=\"scroll-content-item\">\n                    <a href=\"javascript:void(0);\" class=\"on_fous preview_btn\" data-paper_num=\"17\">\n                        <img src=\"http://file30.mafengwo.net/M00/C5/07/wKgBpVWb-iyAZLQTAAyycMAoJSQ30.book.w130.jpeg\" width=\"138\" height=\"195\">\n                        <span>点击<br>预览</span>\n                    </a>\n                </li>\n                            <li class=\"scroll-content-item\">\n                    <a href=\"javascript:void(0);\" class=\"on_fous preview_btn\" data-paper_num=\"18\">\n                        <img src=\"http://file29.mafengwo.net/M00/C5/08/wKgBpVWb-iyAMt2KAA0UOT8UGUA42.book.w130.jpeg\" width=\"138\" height=\"195\">\n                        <span>点击<br>预览</span>\n                    </a>\n                </li>\n                            <li class=\"scroll-content-item\">\n                    <a href=\"javascript:void(0);\" class=\"on_fous preview_btn\" data-paper_num=\"19\">\n                        <img src=\"http://file30.mafengwo.net/M00/C5/09/wKgBpVWb-i2AaWqbAArKJP91iRY38.book.w130.jpeg\" width=\"138\" height=\"195\">\n                        <span>点击<br>预览</span>\n                    </a>\n                </li>\n                            <li class=\"scroll-content-item\">\n                    <a href=\"javascript:void(0);\" class=\"on_fous preview_btn\" data-paper_num=\"20\">\n                        <img src=\"http://file29.mafengwo.net/M00/C5/0A/wKgBpVWb-i2ALAokAAxm28el51M58.book.w130.jpeg\" width=\"138\" height=\"195\">\n                        <span>点击<br>预览</span>\n                    </a>\n                </li>\n                            <li class=\"scroll-content-item\">\n                    <a href=\"javascript:void(0);\" class=\"on_fous preview_btn\" data-paper_num=\"21\">\n                        <img src=\"http://file30.mafengwo.net/M00/C5/0B/wKgBpVWb-i2AT4wUAAygqXJoZr003.book.w130.jpeg\" width=\"138\" height=\"195\">\n                        <span>点击<br>预览</span>\n                    </a>\n                </li>\n                            <li class=\"scroll-content-item\">\n                    <a href=\"javascript:void(0);\" class=\"on_fous preview_btn\" data-paper_num=\"22\">\n                        <img src=\"http://file29.mafengwo.net/M00/C5/0C/wKgBpVWb-i2AeKpQAA1KZ1NHJDs00.book.w130.jpeg\" width=\"138\" height=\"195\">\n                        <span>点击<br>预览</span>\n                    </a>\n                </li>\n                            <li class=\"scroll-content-item\">\n                    <a href=\"javascript:void(0);\" class=\"on_fous preview_btn\" data-paper_num=\"23\">\n                        <img src=\"http://file29.mafengwo.net/M00/C5/0C/wKgBpVWb-i6Ad9GcAAzTX5t6cUA32.book.w130.jpeg\" width=\"138\" height=\"195\">\n                        <span>点击<br>预览</span>\n                    </a>\n                </li>\n                            <li class=\"scroll-content-item\">\n                    <a href=\"javascript:void(0);\" class=\"on_fous preview_btn\" data-paper_num=\"24\">\n                        <img src=\"http://file30.mafengwo.net/M00/C5/0D/wKgBpVWb-i6AL0I_AArPsunQkPo08.book.w130.jpeg\" width=\"138\" height=\"195\">\n                        <span>点击<br>预览</span>\n                    </a>\n                </li>\n                            <li class=\"scroll-content-item\">\n                    <a href=\"javascript:void(0);\" class=\"on_fous preview_btn\" data-paper_num=\"25\">\n                        <img src=\"http://file29.mafengwo.net/M00/C5/0E/wKgBpVWb-i6AfjEuAAzeEpK5bas21.book.w130.jpeg\" width=\"138\" height=\"195\">\n                        <span>点击<br>预览</span>\n                    </a>\n                </li>\n                            <li class=\"scroll-content-item\">\n                    <a href=\"javascript:void(0);\" class=\"on_fous preview_btn\" data-paper_num=\"26\">\n                        <img src=\"http://file30.mafengwo.net/M00/C5/0F/wKgBpVWb-i6AJ33NAAqaNjn_vEg29.book.w130.jpeg\" width=\"138\" height=\"195\">\n                        <span>点击<br>预览</span>\n                    </a>\n                </li>\n                            <li class=\"scroll-content-item\">\n                    <a href=\"javascript:void(0);\" class=\"on_fous preview_btn\" data-paper_num=\"27\">\n                        <img src=\"http://file29.mafengwo.net/M00/C5/10/wKgBpVWb-i-AfEIyAAvCQUR_7r848.book.w130.jpeg\" width=\"138\" height=\"195\">\n                        <span>点击<br>预览</span>\n                    </a>\n                </li>\n                            <li class=\"scroll-content-item\">\n                    <a href=\"javascript:void(0);\" class=\"on_fous preview_btn\" data-paper_num=\"28\">\n                        <img src=\"http://file30.mafengwo.net/M00/C5/11/wKgBpVWb-i-ALL3dAAsmiadrC2480.book.w130.jpeg\" width=\"138\" height=\"195\">\n                        <span>点击<br>预览</span>\n                    </a>\n                </li>\n                            <li class=\"scroll-content-item\">\n                    <a href=\"javascript:void(0);\" class=\"on_fous preview_btn\" data-paper_num=\"29\">\n                        <img src=\"http://file30.mafengwo.net/M00/C5/11/wKgBpVWb-i-AUo_5AApgd_EOdvA16.book.w130.jpeg\" width=\"138\" height=\"195\">\n                        <span>点击<br>预览</span>\n                    </a>\n                </li>\n                            <li class=\"scroll-content-item\">\n                    <a href=\"javascript:void(0);\" class=\"on_fous preview_btn\" data-paper_num=\"30\">\n                        <img src=\"http://file29.mafengwo.net/M00/C5/12/wKgBpVWb-i-ACmMJAA1JD2M4K9075.book.w130.jpeg\" width=\"138\" height=\"195\">\n                        <span>点击<br>预览</span>\n                    </a>\n                </li>\n                            <li class=\"scroll-content-item\">\n                    <a href=\"javascript:void(0);\" class=\"on_fous preview_btn\" data-paper_num=\"31\">\n                        <img src=\"http://file30.mafengwo.net/M00/C5/13/wKgBpVWb-jCATLurAAqkIj_Bl4w13.book.w130.jpeg\" width=\"138\" height=\"195\">\n                        <span>点击<br>预览</span>\n                    </a>\n                </li>\n                            <li class=\"scroll-content-item\">\n                    <a href=\"javascript:void(0);\" class=\"on_fous preview_btn\" data-paper_num=\"32\">\n                        <img src=\"http://file29.mafengwo.net/M00/C5/14/wKgBpVWb-jCAEzRQAAp6NdkQKgA66.book.w130.jpeg\" width=\"138\" height=\"195\">\n                        <span>点击<br>预览</span>\n                    </a>\n                </li>\n                            <li class=\"scroll-content-item\">\n                    <a href=\"javascript:void(0);\" class=\"on_fous preview_btn\" data-paper_num=\"33\">\n                        <img src=\"http://file30.mafengwo.net/M00/C5/15/wKgBpVWb-jCAO9GBAAmy_LHkVuk48.book.w130.jpeg\" width=\"138\" height=\"195\">\n                        <span>点击<br>预览</span>\n                    </a>\n                </li>\n                            <li class=\"scroll-content-item\">\n                    <a href=\"javascript:void(0);\" class=\"on_fous preview_btn\" data-paper_num=\"34\">\n                        <img src=\"http://file30.mafengwo.net/M00/C5/17/wKgBpVWb-jGAJTmQAAtj0w55hks12.book.w130.jpeg\" width=\"138\" height=\"195\">\n                        <span>点击<br>预览</span>\n                    </a>\n                </li>\n                            <li class=\"scroll-content-item\">\n                    <a href=\"javascript:void(0);\" class=\"on_fous preview_btn\" data-paper_num=\"35\">\n                        <img src=\"http://file30.mafengwo.net/M00/C5/17/wKgBpVWb-jGAM96VAAu0YKw1BHU88.book.w130.jpeg\" width=\"138\" height=\"195\">\n                        <span>点击<br>预览</span>\n                    </a>\n                </li>\n                            <li class=\"scroll-content-item\">\n                    <a href=\"javascript:void(0);\" class=\"on_fous preview_btn\" data-paper_num=\"36\">\n                        <img src=\"http://file29.mafengwo.net/M00/C5/18/wKgBpVWb-jGAVE3FAAqduMn8Olg68.book.w130.jpeg\" width=\"138\" height=\"195\">\n                        <span>点击<br>预览</span>\n                    </a>\n                </li>\n                            <li class=\"scroll-content-item\">\n                    <a href=\"javascript:void(0);\" class=\"on_fous preview_btn\" data-paper_num=\"37\">\n                        <img src=\"http://file30.mafengwo.net/M00/C5/19/wKgBpVWb-jGAJFB0AAp0V7xypYY25.book.w130.jpeg\" width=\"138\" height=\"195\">\n                        <span>点击<br>预览</span>\n                    </a>\n                </li>\n                            <li class=\"scroll-content-item\">\n                    <a href=\"javascript:void(0);\" class=\"on_fous preview_btn\" data-paper_num=\"38\">\n                        <img src=\"http://file29.mafengwo.net/M00/C5/1A/wKgBpVWb-jKALcxeAAmUo-SVZzI26.book.w130.jpeg\" width=\"138\" height=\"195\">\n                        <span>点击<br>预览</span>\n                    </a>\n                </li>"}